pinstall/__init__.py
pinstall/__main__.py
pinstall/getpy.py
pinstall/pinstall.py
pinstall/pyproj.py
pinstall/run.py
pinstall/commands/project.py
pinstall/commands/pyenv.py
pinstall/commands/service.py
pinstall/commands/status.py
pinstall/commands/uv.py
pinstall/commands/venv-legacy.py
pinstall/commands/venv.py
pinstall/commands/version.py
pinstall-1.23.dist-info/METADATA
pinstall-1.23.dist-info/WHEEL
pinstall-1.23.dist-info/entry_points.txt
pinstall-1.23.dist-info/top_level.txt
pinstall-1.23.dist-info/RECORD
