Metadata-Version: 2.4
Name: pinstall
Version: 1.23
Summary: Installer Tool for Python Programs
Author-email: Mark Blakeney <mark.blakeney@bullet-systems.net>
License-Expression: GPL-3.0-or-later
Project-URL: Homepage, https://github.com/bulletmark/pinstall
Keywords: venv,virtualenv,systemd,service,pip,pipx,pyproject.toml
Classifier: Programming Language :: Python :: 3
Requires-Python: >=3.8
Requires-Dist: argcomplete
Requires-Dist: packaging
Requires-Dist: tomli>=1.1.0; python_version < "3.11"
Requires-Dist: importlib-metadata; python_version < "3.8"
